{
  "name": "Binary Ex2",
  "nodes": [
    {
      "parameters": {},
      "type": "n8n-nodes-base.manualTrigger",
      "typeVersion": 1,
      "position": [
        0,
        0
      ],
      "id": "17bf78d9-16e5-497c-854b-17016beaf4c7",
      "name": "When clicking ‘Execute workflow’"
    },
    {
      "parameters": {
        "url": "https://poetrydb.org/random/1",
        "options": {}
      },
      "type": "n8n-nodes-base.httpRequest",
      "typeVersion": 4.2,
      "position": [
        208,
        0
      ],
      "id": "7e7ccd16-ca28-4a3d-8bec-a6ec2c862afa",
      "name": "HTTP Request"
    },
    {
      "parameters": {
        "operation": "toJson",
        "options": {}
      },
      "type": "n8n-nodes-base.convertToFile",
      "typeVersion": 1.1,
      "position": [
        416,
        0
      ],
      "id": "fa1d89fc-56be-4404-98de-179d3745f51e",
      "name": "Convert to File"
    },
    {
      "parameters": {
        "fileSelector": "Desktop/YC/abc.pdf",
        "options": {}
      },
      "type": "n8n-nodes-base.readWriteFile",
      "typeVersion": 1,
      "position": [
        624,
        0
      ],
      "id": "b30aea85-7af9-49b1-9851-b8874b34ec6d",
      "name": "Read/Write Files from Disk"
    }
  ],
  "connections": {
    "When clicking ‘Execute workflow’": {
      "main": [
        [
          {
            "node": "HTTP Request",
            "type": "main",
            "index": 0
          }
        ]
      ]
    },
    "HTTP Request": {
      "main": [
        [
          {
            "node": "Convert to File",
            "type": "main",
            "index": 0
          }
        ]
      ]
    },
    "Convert to File": {
      "main": [
        [
          {
            "node": "Read/Write Files from Disk",
            "type": "main",
            "index": 0
          }
        ]
      ]
    }
  },
  "settings": {
    "executionOrder": "v1"
  },
  "staticData": null,
  "pinData": {},
  "triggerCount": 0,
  "meta": null
}